README.rst
setup.py
fillmydb/__init__.py
fillmydb.egg-info/PKG-INFO
fillmydb.egg-info/SOURCES.txt
fillmydb.egg-info/dependency_links.txt
fillmydb.egg-info/requires.txt
fillmydb.egg-info/top_level.txt
fillmydb/core/__init__.py
fillmydb/handlers/__init__.py
fillmydb/handlers/base_handler.py
fillmydb/handlers/peewee.py