Metadata-Version: 1.1
Name: fillmydb
Version: 0.1.0
Summary: Fill your database with mocked instances.
Home-page: https://github.com/vladcalin/fillmydb
Author: Calin Vlad
Author-email: vlad.s.calin@gmail.com
License: MIT
Platform: UNKNOWN
Classifier: License :: OSI Approved :: MIT License
Classifier: Programming Language :: Python :: 3.4
Classifier: Programming Language :: Python :: 3.5
Classifier: Programming Language :: Python :: 3.6
Classifier: Topic :: Database
